.gitignore
LICENSE
MANIFEST.in
NAME
PKG-INFO
README.md
VERSION
setup.cfg
setup.py
data_amqp/__init__.py
data_amqp/amqp.py
tests/ampq.py
tests/consumir.py
tests/gendata.py