Metadata-Version: 2.1
Name: data_amqp
Version: 0.1.16
Summary: DataDBS for RabbitMQP
Home-page: http://www.gitlab.com/dpineda/data_amqp
Author: David Pineda Osorio
Author-email: dpineda@csn.uchile.cl
License: GPLv3
Platform: UNKNOWN
